{"title":"The.Script.No.Sound.Without.Silence.2014.FLAC.iSAAC","uid":11410056,"size":324080678,"categoryP":"audio","categoryS":"flac","magnet":"?xt=urn:btih:0285963364c73ab0bed20e2fd0f67e60f43e06af&amp;dn=The.Script.No.Sound.Without.Silence.2014.FLAC.iSAAC&amp;tr=udp%3A%2F%2Ftracker.openbittorrent.com%3A80&amp;tr=udp%3A%2F%2Fopen.demonii.com%3A1337&amp;tr=udp%3A%2F%2Ftracker.coppersurfer.tk%3A6969&amp;tr=udp%3A%2F%2Fexodus.desync.com%3A6969","seeders":27,"leechers":1,"uploader":"Isaac09","files":-1,"time":1415520424,"description":"The.Script.No.Sound.Without.Silence.2014.FLAC.iSAAC\n\n\nARTIST........: The Script\nALBUM.........: No Sound Without Silence - Standard Version\nRELEASED......: September 12, 2014\nRUNTIME.......: 43mn 57sec\nAUDIO CODEC...: FLAC\nSAMPLING RATE.: 44.1 KHz \nBIT DEPTH.....: 16 Bits \nBITRATE.......: ~1 Mbps\nSOURCE........: Retail CD \nGENRE.........: Pop Rock\nLABEL.........: Phonogenic, Columbia\nPRODUCER......: James Barry, Andrew Frampton, Steve Kipner, Danny O'Donoghue, Mark Sheehan\n\n\nNo Sound Without Silence is the fourth studio album by Irish pop rock band The Script. The album was released by Columbia Records on 12 September 2014 in Ireland and Friday-release countries and on 15 September 2014 in the United Kingdom. The album is the band's first full-length release under Columbia, after releasing their previous three studio albums under Phonogenic Records in Europe and Epic Records in the United States.\n\n\nFormat                                   : FLAC\nFormat/Info                              : Free Lossless Audio Codec\nFile size                                : 37.8 MiB\nDuration                                 : 5mn 7s\nOverall bit rate mode                    : Variable\nOverall bit rate                         : 1 031 Kbps\nAlbum                                    : No Sound Without Silence\nAlbum/Performer                          : The Script\nPart                                     : 1\nPart/Total                               : 1\nTrack name                               : No Good in Goodbye\nTrack name/Position                      : 1\nTrack name/Total                         : 11\nPerformer                                : The Script\nLabel                                    : Sony Music\nRecorded date                            : 2014\nCover                                    : Yes\nCover type                               : Cover (front)\nCover MIME                               : image/jpeg\nRELEASECOUNTRY                           : GB\nMUSICBRAINZ_RELEASETRACKID               : 2bc92f06-8efd-443a-b0ac-e0e7a2fdc1af\nASIN                                     : B00M0CVY6K\nALBUMARTISTSORT                          : Script, The\nORIGINALDATE                             : 2014-07-28\nSCRIPT                                   : Latn\nRELEASESTATUS                            : official\nCATALOGNUMBER                            : 88843097392\nMEDIA                                    : CD\nRELEASETYPE                              : album\nMUSICBRAINZ_RELEASEGROUPID               : 5e084a94-8228-4a81-81b5-7579e03291e9\nBARCODE                                  : 888430973923\nARTISTSORT                               : Script, The\nARTISTS                                  : The Script\n\nAudio\nFormat                                   : FLAC\nFormat/Info                              : Free Lossless Audio Codec\nDuration                                 : 5mn 7s\nBit rate mode                            : Variable\nBit rate                                 : 1 018 Kbps\nChannel(s)                               : 2 channels\nSampling rate                            : 44.1 KHz\nBit depth                                : 16 bits\nStream size                              : 37.4 MiB (99%)\nWriting library                          : libFLAC 1.2.1 (UTC 2007-09-17)\n\n-----------------------\n\nDON'T MODIFY THIS FILE\n\n-----------------------\n\nPERFORMER: auCDtect Task Manager, ver. 1.6.0 RC1 build 1.6.0.1\nCopyright (c) 2008-2010 y-soft. All rights reserved &lt;a href=&quot;\nhttp://y-soft.org&quot; rel=&quot;nofollow&quot; target=&quot;_NEW&quot;&gt;\nhttp://y-soft.org&lt;/a&gt;\n\nANALYZER: auCDtect: CD records authenticity detector, version 0.8.2\nCopyright (c) 2004 Oleg Berngardt. All rights reserved.\nCopyright (c) 2004 Alexander Djourik. All rights reserved.\n\n\nFILE: 11 Hail Rain or Sunshine.flac\n  Size: 24593407 Hash: E2D071702883CF88ADD14525027728F5 Accuracy: -m0\n  Conclusion: CDDA 100%\n  Signature: 9B9692B58ACD009C3241DB169B5FA383021F112A\nFILE: 10 Without Those Songs.flac\n  Size: 25967473 Hash: 8714389EC2A631D187E151DAD1B0F975 Accuracy: -m0\n  Conclusion: MPEG 95%\n  Signature: 9E18D0E59FA54C59C74B119652A1CA1CFA567722\nFILE: 09 Paint the Town Green.flac\n  Size: 27551983 Hash: AE202689CF1E41AAE7887B0F94BE7287 Accuracy: -m0\n  Conclusion: CDDA 100%\n  Signature: FA65FC735EBBEE606C215F8C5455EDAE48359C02\nFILE: 08 Never Seen Anything Quite Like You.flac\n  Size: 22484075 Hash: 8C57184A32376E68232523B4A8FDCFBC Accuracy: -m0\n  Conclusion: CDDA 100%\n  Signature: A7E41D5F0C266F0CF3F9B35BF57AC47235785BD3\nFILE: 07 Army of Angels.flac\n  Size: 28322619 Hash: ADC6463A00AC9D6DF7A3F5318B59069C Accuracy: -m0\n  Conclusion: MPEG 95%\n  Signature: 9024400DF515F8FA5C73502FB2E107CD193D4EF2\nFILE: 06 Flares.flac\n  Size: 23776685 Hash: 0BBA53A7439C9ECA69435B86288218F9 Accuracy: -m0\n  Conclusion: MPEG 95%\n  Signature: 61F1B7E5ECDF896BCB8A7451D1CE00793A58319D\nFILE: 05 The Energy Never Dies.flac\n  Size: 30964312 Hash: EE6A01B71BC6FBD2F406EE79D799E9E0 Accuracy: -m0\n  Conclusion: CDDA 100%\n  Signature: C3F538F18718E44CA57E2F14DF8756DBE2F859AD\nFILE: 04 It's Not Right for You.flac\n  Size: 32340239 Hash: 8A75050D0F29477F51A63D4674097287 Accuracy: -m0\n  Conclusion: CDDA 100%\n  Signature: 870E5BE0EB323E9F8335CF6E29D2E028C69CF0A3\nFILE: 03 Man on a Wire.flac\n  Size: 32387496 Hash: A5A4B6151EDF05C90F938E0063A95C70 Accuracy: -m0\n  Conclusion: CDDA 100%\n  Signature: 138875E1BDF462A87A43939E5ABB0B0F950D8940\nFILE: 02 Superheroes.flac\n  Size: 30680507 Hash: 8A7E0D9AE1496E0A3E41ECF9230FE4DF Accuracy: -m0\n  Conclusion: CDDA 100%\n  Signature: 8A49F6106A3623EA3F7E9EB86E4002F50D085AF6\nFILE: 01 No Good in Goodbye.flac\n  Size: 39179244 Hash: 1B8264276FFD9AB46DF70DF0148965D8 Accuracy: -m0\n  Conclusion: CDDA 100%\n  Signature: 909EB7CA717CF42F1C67DAA8542E811D9B30C3CC","torrent":{"xt":"urn:btih:0285963364c73ab0bed20e2fd0f67e60f43e06af","amp;dn":"The.Script.No.Sound.Without.Silence.2014.FLAC.iSAAC","amp;tr":["udp%3A%2F%2Ftracker.openbittorrent.com%3A80","udp%3A%2F%2Fopen.demonii.com%3A1337","udp%3A%2F%2Ftracker.coppersurfer.tk%3A6969","udp%3A%2F%2Fexodus.desync.com%3A6969"],"infoHash":"0285963364c73ab0bed20e2fd0f67e60f43e06af","infoHashBuffer":{"type":"Buffer","data":[2,133,150,51,100,199,58,176,190,210,14,47,208,246,126,96,244,62,6,175]},"announce":[],"urlList":[]}}