{"title":"The Taking of Deborah Logan 2014 HDRip Xvid","uid":11598948,"size":940249368,"categoryP":"video","categoryS":"movies","magnet":"?xt=urn:btih:5b36519b0acb068faf6cf8265069132c94a8f785&amp;dn=The+Taking+of+Deborah+Logan+2014+HDRip+Xvid&amp;tr=udp%3A%2F%2Ftracker.openbittorrent.com%3A80&amp;tr=udp%3A%2F%2Fopen.demonii.com%3A1337&amp;tr=udp%3A%2F%2Ftracker.coppersurfer.tk%3A6969&amp;tr=udp%3A%2F%2Fexodus.desync.com%3A6969","seeders":33,"leechers":5,"uploader":"makintos13","files":2,"time":1417318403,"description":" &lt;a href=&quot;http://imgsleek.com/img-547a81a71933f.html&quot; rel=&quot;nofollow&quot; target=&quot;_NEW&quot;&gt;http://imgsleek.com/img-547a81a71933f.html&lt;/a&gt;\n &lt;a href=&quot;\nhttp://imgsleek.com/img-547a81a71f450.html&quot; rel=&quot;nofollow&quot; target=&quot;_NEW&quot;&gt;\nhttp://imgsleek.com/img-547a81a71f450.html&lt;/a&gt;\n &lt;a href=&quot;\nhttp://imgsleek.com/img-547a81a724b63.html&quot; rel=&quot;nofollow&quot; target=&quot;_NEW&quot;&gt;\nhttp://imgsleek.com/img-547a81a724b63.html&lt;/a&gt;\n &lt;a href=&quot;\nhttp://imgsleek.com/img-547a81a72a2bf.html&quot; rel=&quot;nofollow&quot; target=&quot;_NEW&quot;&gt;\nhttp://imgsleek.com/img-547a81a72a2bf.html&lt;/a&gt;\n\n...........................................................\n &lt;a href=&quot;\nhttp://www.imdb.com/title/tt3387648/&quot; rel=&quot;nofollow&quot; target=&quot;_NEW&quot;&gt;\nhttp://www.imdb.com/title/tt3387648/&lt;/a&gt;","torrent":{"xt":"urn:btih:5b36519b0acb068faf6cf8265069132c94a8f785","amp;dn":"The+Taking+of+Deborah+Logan+2014+HDRip+Xvid","amp;tr":["udp%3A%2F%2Ftracker.openbittorrent.com%3A80","udp%3A%2F%2Fopen.demonii.com%3A1337","udp%3A%2F%2Ftracker.coppersurfer.tk%3A6969","udp%3A%2F%2Fexodus.desync.com%3A6969"],"infoHash":"5b36519b0acb068faf6cf8265069132c94a8f785","infoHashBuffer":{"type":"Buffer","data":[91,54,81,155,10,203,6,143,175,108,248,38,80,105,19,44,148,168,247,133]},"announce":[],"urlList":[]}}