{"title":"OneRepublic - Oh My My (Deluxe) (2016) [FLAC CD]","uid":15976132,"size":524400354,"categoryP":"audio","categoryS":"flac","magnet":"?xt=urn:btih:7059eba02dfce14e31870f8dfc4ca779e6ae030d&amp;dn=+OneRepublic+-+Oh+My+My+%28Deluxe%29+%282016%29+%5BFLAC+CD%5D&amp;tr=udp%3A%2F%2Ftracker.leechers-paradise.org%3A6969&amp;tr=udp%3A%2F%2Fzer0day.ch%3A1337&amp;tr=udp%3A%2F%2Fopen.demonii.com%3A1337&amp;tr=udp%3A%2F%2Ftracker.coppersurfer.tk%3A6969&amp;tr=udp%3A%2F%2Fexodus.desync.com%3A6969","seeders":33,"leechers":4,"uploader":"Freak0370","files":22,"time":1475842744,"description":"Artist: OneRepublic\r\nTitle: Oh My My (Deluxe)\r\nYear Of Release: 2016\r\nLabel: Mosley Music / Interscope Records\r\nGenre: Pop\r\nQuality: FLAC (tracks)\r\nTotal Time: 75:29 min\r\nTotal Size: 500 MB\r\n\r\n\r\n\r\n01. Letâ™s Hurt Tonight [03:14]\r\n02. Future Looks Good [03:30]\r\n03. Oh My My [03:38]\r\n04. Kids [03:58]\r\n05. Dream [03:31]\r\n06. Choke [03:46]\r\n07. A.I [05:09]\r\n08. Better [03:24]\r\n09. Born [04:25]\r\n10. Fingertips [04:15]\r\n11. Human [03:40]\r\n12. Lift Me Up [03:46]\r\n13. NbHD [03:44]\r\n14. Wherever I Go [02:49]\r\n15. All These Things [03:19]\r\n16. Heaven [04:18]\r\n17. Colors [03:51]\r\n18. The Less I Know [03:44]\r\n19. Heaven (Acoustic) [03:53]\r\n20. Better (String Version) [03:23] \r\n\r\n \nhttps://extraimago.com/image/wKeo","torrent":{"xt":"urn:btih:7059eba02dfce14e31870f8dfc4ca779e6ae030d","amp;dn":"+OneRepublic+-+Oh+My+My+%28Deluxe%29+%282016%29+%5BFLAC+CD%5D","amp;tr":["udp%3A%2F%2Ftracker.leechers-paradise.org%3A6969","udp%3A%2F%2Fzer0day.ch%3A1337","udp%3A%2F%2Fopen.demonii.com%3A1337","udp%3A%2F%2Ftracker.coppersurfer.tk%3A6969","udp%3A%2F%2Fexodus.desync.com%3A6969"],"infoHash":"7059eba02dfce14e31870f8dfc4ca779e6ae030d","infoHashBuffer":{"type":"Buffer","data":[112,89,235,160,45,252,225,78,49,135,15,141,252,76,167,121,230,174,3,13]},"announce":[],"urlList":[]}}