{"title":"Vicetone - Heat (Original Mix)","uid":10803494,"size":14048631,"categoryP":"audio","categoryS":"music","magnet":"?xt=urn:btih:7a4cb2fc1b9713b4d20203b1c3fb94cfe6e11072&amp;dn=Vicetone+-+Heat+%28Original+Mix%29&amp;tr=udp%3A%2F%2Ftracker.openbittorrent.com%3A80&amp;tr=udp%3A%2F%2Fopen.demonii.com%3A1337&amp;tr=udp%3A%2F%2Ftracker.coppersurfer.tk%3A6969&amp;tr=udp%3A%2F%2Fexodus.desync.com%3A6969","seeders":21,"leechers":0,"uploader":"pamabego","files":-1,"time":1408368501,"description":" &lt;a href=&quot;http://www.beatport.com/release/heat/1359823&quot; rel=&quot;nofollow&quot; target=&quot;_NEW&quot;&gt;http://www.beatport.com/release/heat/1359823&lt;/a&gt;\n\n\n\nFormat                                   : MPEG Audio\nFile size                                : 13.4 MiB\nDuration                                 : 5mn 49s\nOverall bit rate mode                    : Constant\nOverall bit rate                         : 320 Kbps\nAlbum                                    : Heat\nTrack name                               : Heat (Original Mix)\nPerformer                                : Vicetone\nGenre                                    : Progressive House\nRecorded date                            : 2014\nWriting library                          : LAME3.93 \nCover                                    : Yes\nCover type                               : Cover (front)\nCover MIME                               : image/jpg\nURL                                      : Heat \n\n\nAudio\nFormat                                   : MPEG Audio\nFormat version                           : Version 1\nFormat profile                           : Layer 3\nDuration                                 : 5mn 50s\nBit rate mode                            : Constant\nBit rate                                 : 320 Kbps\nChannel(s)                               : 2 channels\nSampling rate                            : 44.1 KHz\nCompression mode                         : Lossy\nStream size                              : 13.3 MiB (100%)\nWriting library                          : LAME3.93 \nEncoding settings                        : -m s -V 4 -q 2 -lowpass 21.4\n\n","torrent":{"xt":"urn:btih:7a4cb2fc1b9713b4d20203b1c3fb94cfe6e11072","amp;dn":"Vicetone+-+Heat+%28Original+Mix%29","amp;tr":["udp%3A%2F%2Ftracker.openbittorrent.com%3A80","udp%3A%2F%2Fopen.demonii.com%3A1337","udp%3A%2F%2Ftracker.coppersurfer.tk%3A6969","udp%3A%2F%2Fexodus.desync.com%3A6969"],"infoHash":"7a4cb2fc1b9713b4d20203b1c3fb94cfe6e11072","infoHashBuffer":{"type":"Buffer","data":[122,76,178,252,27,151,19,180,210,2,3,177,195,251,148,207,230,225,16,114]},"announce":[],"urlList":[]}}