{"title":"The Shallows (2016) 720p BluRay - x265 HEVC - 550MB - ShAaNiG","uid":15801124,"size":577212270,"categoryP":"video","categoryS":"hd___movies","magnet":"?xt=urn:btih:b6e17a81abbed9781b28a5ff420df6f0209b00c3&amp;dn=The+Shallows+%282016%29+720p+BluRay+-+x265+HEVC+-+550MB+-+ShAaNiG&amp;tr=udp%3A%2F%2Ftracker.leechers-paradise.org%3A6969&amp;tr=udp%3A%2F%2Fzer0day.ch%3A1337&amp;tr=udp%3A%2F%2Fopen.demonii.com%3A1337&amp;tr=udp%3A%2F%2Ftracker.coppersurfer.tk%3A6969&amp;tr=udp%3A%2F%2Fexodus.desync.com%3A6969","seeders":25,"leechers":11,"uploader":"ShAaNiG","files":1,"time":1473503750,"description":"\n-: SCREENSHOTS :-\r\n \nhttps://www.shaanig.org/f93/shallows-2016-720p-bluray-x265-hevc-550mb-shaanig-4801809/\r\n\r\n\r\n-: RELEASENOTES :-\r\n\r\n[NAME]:.........................[ The Shallows\r\n[DIRECTOR]:.....................[ Jaume Collet-Serra\r\n[RELEASE DATE]:.................[ 24 June 2016 (USA)\r\n[GENRE]:........................[ Drama, Horror, Thriller\r\n[HDTV SUPPORT]:.................[ Yes\r\n[NO OF FILES]:..................[ 1\r\n[VIDEO]:........................[ MKV - x265 HEVC\r\n[AUDIO]:........................[ AAC - 2CH\r\n[FILE SIZE]:....................[ 550MB\r\n[RESOLUTION]:...................[ 1280x536\r\n[FRAME RATE]:...................[ 23.976 fps\r\n[LANGUAGE]:.....................[ English\r\n[RUNTIME]:......................[ 01:26:16\r\n[ENCODER]:......................[ ShAaNiG\r\n[SOURCE]:.......................[ 1080p.BluRay-GECKOS","torrent":{"xt":"urn:btih:b6e17a81abbed9781b28a5ff420df6f0209b00c3","amp;dn":"The+Shallows+%282016%29+720p+BluRay+-+x265+HEVC+-+550MB+-+ShAaNiG","amp;tr":["udp%3A%2F%2Ftracker.leechers-paradise.org%3A6969","udp%3A%2F%2Fzer0day.ch%3A1337","udp%3A%2F%2Fopen.demonii.com%3A1337","udp%3A%2F%2Ftracker.coppersurfer.tk%3A6969","udp%3A%2F%2Fexodus.desync.com%3A6969"],"infoHash":"b6e17a81abbed9781b28a5ff420df6f0209b00c3","infoHashBuffer":{"type":"Buffer","data":[182,225,122,129,171,190,217,120,27,40,165,255,66,13,246,240,32,155,0,195]},"announce":[],"urlList":[]}}