{"title":"The Outfield - The Best Of The Outfield (1996) [MP3 192]","uid":7149814,"size":87719134,"categoryP":"audio","categoryS":"music","magnet":"?xt=urn:btih:c039894ecc8c3ff732c121d9525e22e4874dd08e&amp;dn=The+Outfield+-+The+Best+Of+The+Outfield+%281996%29+%5BMP3+192%5D&amp;tr=udp%3A%2F%2Ftracker.openbittorrent.com%3A80&amp;tr=udp%3A%2F%2Fopen.demonii.com%3A1337&amp;tr=udp%3A%2F%2Ftracker.coppersurfer.tk%3A6969&amp;tr=udp%3A%2F%2Fexodus.desync.com%3A6969","seeders":34,"leechers":4,"uploader":"Stepherd","files":-1,"time":1333276735,"description":"Bit Rate: 192 \nSample Rate: 44.100 kHz \n\n1. Voices Of Babylon \n2. For You \n3. Your Love \n4. It Should Have Been Me \n5. Say It Isn't So \n6. Winning It All \n7. Everytime You Cry \n8. Through The Years \n9. The Night Ain't Over \n10. Closer To Me \n11. Somewhere In America '89 \n12. My Paradise \n13. All The Love \n14. Alone With You \n15. Since You've Been Gone \n16. One Hot Country \n\nEnjoy!","torrent":{"xt":"urn:btih:c039894ecc8c3ff732c121d9525e22e4874dd08e","amp;dn":"The+Outfield+-+The+Best+Of+The+Outfield+%281996%29+%5BMP3+192%5D","amp;tr":["udp%3A%2F%2Ftracker.openbittorrent.com%3A80","udp%3A%2F%2Fopen.demonii.com%3A1337","udp%3A%2F%2Ftracker.coppersurfer.tk%3A6969","udp%3A%2F%2Fexodus.desync.com%3A6969"],"infoHash":"c039894ecc8c3ff732c121d9525e22e4874dd08e","infoHashBuffer":{"type":"Buffer","data":[192,57,137,78,204,140,63,247,50,193,33,217,82,94,34,228,135,77,208,142]},"announce":[],"urlList":[]}}