{"title":"Gary Clark Jr. - Blak And Blu(2013)(MP3@320Kbps)-TBS","uid":8151444,"size":181055590,"categoryP":"audio","categoryS":"other","magnet":"?xt=urn:btih:cddcc96e7aae78d49a54beb85399328e53c6d61d&amp;dn=Gary+Clark+Jr.+-+Blak+And+Blu%282013%29%28MP3%40320Kbps%29-TBS&amp;tr=udp%3A%2F%2Ftracker.openbittorrent.com%3A80&amp;tr=udp%3A%2F%2Fopen.demonii.com%3A1337&amp;tr=udp%3A%2F%2Ftracker.coppersurfer.tk%3A6969&amp;tr=udp%3A%2F%2Fexodus.desync.com%3A6969","seeders":24,"leechers":3,"uploader":"Nobby010","files":-1,"time":1361046043,"description":"Gary Clark Jr. - Blak And Blu *2013*\n\nHet langverwachte debuutalbum van Gary Clark Jr. heet Blak and Blu. Gary Clark Jr. draagt de goedkeuring van onder andere Paul McCartney, Eric Clapton, Neil Young, Jimmy Page, The Roots en zelfs President Obama. The Rolling Stones waren zo onder de indruk dat ze hem hebben gevraagd mee te doen tijdens hun eerste show van de de tour 50 and Counting in New York.\nHet album is geproduceerd door de veelzijdige Mike Elizondo, wie eerder verantwoordelijk was voor albums van onder meer Dr. Dre, Maroon 5, en Eli 'Paperboy' Reed.\nThe New York times noemde Clark a guitarist of deep magnetism and tremendous feel.\nDe Amerikanen zijn laaiend enthousiast, nu wij nog.\n\nVerenigde Staten\nBlues / Rock\nLabel: Warner Bros.\n\nTracklist:\n1. Ain&amp;# 39;t Messin 'Round\n2. When My Train Pulls In\n3. Blak and Blu\n4. Bright Lights\n5. Travis County\n6. The Life\n7. Glitter Ain't Gold (Jumpin' For Nothin')\n8. Numb\n9. Please Come Home\n10. Things Are Changin'\n11. Third Stone From the Sun/If You Love Me Like You Say\n12. You Saved Me\n13. Next Door Neighbor Blues \n\n\nHQ COVERS INCLUDED!!!\n\nCategory.....:Sound\nFormat.......:MP3\nSource.......:CD \nBitrate......:320 Kbps\nGenre........:Blues / Rock\nThanks.......:Catweazel\n\n\n@@@@@@@@@@@@@@@@@@@@@@@@@@@@@@@","torrent":{"xt":"urn:btih:cddcc96e7aae78d49a54beb85399328e53c6d61d","amp;dn":"Gary+Clark+Jr.+-+Blak+And+Blu%282013%29%28MP3%40320Kbps%29-TBS","amp;tr":["udp%3A%2F%2Ftracker.openbittorrent.com%3A80","udp%3A%2F%2Fopen.demonii.com%3A1337","udp%3A%2F%2Ftracker.coppersurfer.tk%3A6969","udp%3A%2F%2Fexodus.desync.com%3A6969"],"infoHash":"cddcc96e7aae78d49a54beb85399328e53c6d61d","infoHashBuffer":{"type":"Buffer","data":[205,220,201,110,122,174,120,212,154,84,190,184,83,153,50,142,83,198,214,29]},"announce":[],"urlList":[]}}