{"title":"The Complete Riggers Apprentice - 2nd Ed (2016) (Epub) Gooner","uid":15968711,"size":43833287,"categoryP":"other","categoryS":"e_books","magnet":"?xt=urn:btih:d3039a16abdb84dd367ca5376810728408f22679&amp;dn=The+Complete+Riggers+Apprentice+-+2nd+Ed+%282016%29+%28Epub%29+Gooner&amp;tr=udp%3A%2F%2Ftracker.leechers-paradise.org%3A6969&amp;tr=udp%3A%2F%2Fzer0day.ch%3A1337&amp;tr=udp%3A%2F%2Fopen.demonii.com%3A1337&amp;tr=udp%3A%2F%2Ftracker.coppersurfer.tk%3A6969&amp;tr=udp%3A%2F%2Fexodus.desync.com%3A6969","seeders":23,"leechers":2,"uploader":"GoonerTPB","files":2,"time":1475753025,"description":"The Complete Riggers Apprentice - Tools and Techniques for Modern and Traditional Rigging - 2nd Edition (2016) (Epub) Gooner\r\n\r\nPublisher: International Marine/Ragged Mountain Press; 2 edition (20 Sept. 2016)\r\nLanguage: English\r\nISBN-10: 0071849785\r\nISBN-13: 978-0071849784\r\n\r\nRevised and updated―the only book you need on sailboat rigging and marlinspike arts\r\n\r\nFrom its initial publication, The Complete Rigger’s Apprentice has been the definitive go-to resource for weekend sailors and maritime professionals who want to master the fine art of rigging. In this revised second edition, master rigger Brion Toss expands upon the traditional basics of ropeworking to give you the most comprehensive, up-to-date information on the latest tools, techniques, and tricks of the trade.\r\n\r\nFeatures include:\r\n\r\n* A complete rigging primer of essential gear, principles, and procedures\r\n\r\n* Classic ropeworking techniques you can adapt for today’s modern rigs\r\n\r\n* Money-saving tips on the newest equipment, materials, upgrades and designs\r\n\r\n* Illustrated instructions for tying knots, splicing rope, and making repairs\r\n\r\n* Professional guidelines for inspecting and maintaining rigs for longer voyages\r\n\r\n* Emergency procedures, troubleshooters and fixes to ensure smooth sailing\r\n\r\n* New technologies for multihull rigs, soft-shackles, Sta-Lok terminals, and more \r\n\r\n* Need-to-know resources including a portfolio of rigs and glossary of terms\r\n\r\n* PLUS rope tricks and puzzles that will delight your passengers","torrent":{"xt":"urn:btih:d3039a16abdb84dd367ca5376810728408f22679","amp;dn":"The+Complete+Riggers+Apprentice+-+2nd+Ed+%282016%29+%28Epub%29+Gooner","amp;tr":["udp%3A%2F%2Ftracker.leechers-paradise.org%3A6969","udp%3A%2F%2Fzer0day.ch%3A1337","udp%3A%2F%2Fopen.demonii.com%3A1337","udp%3A%2F%2Ftracker.coppersurfer.tk%3A6969","udp%3A%2F%2Fexodus.desync.com%3A6969"],"infoHash":"d3039a16abdb84dd367ca5376810728408f22679","infoHashBuffer":{"type":"Buffer","data":[211,3,154,22,171,219,132,221,54,124,165,55,104,16,114,132,8,242,38,121]},"announce":[],"urlList":[]}}