{"title":"Raaz Reboot (2016) Hindi DesiScrRip 1CD x264 AAC [Kp]","uid":15841424,"size":698071897,"categoryP":"video","categoryS":"movies","magnet":"?xt=urn:btih:d726d7422000b5a43e1f3900a914064def99aa10&amp;dn=Raaz+Reboot+%282016%29+Hindi+DesiScrRip+1CD+x264+AAC+%5BKp%5D&amp;tr=udp%3A%2F%2Ftracker.leechers-paradise.org%3A6969&amp;tr=udp%3A%2F%2Fzer0day.ch%3A1337&amp;tr=udp%3A%2F%2Fopen.demonii.com%3A1337&amp;tr=udp%3A%2F%2Ftracker.coppersurfer.tk%3A6969&amp;tr=udp%3A%2F%2Fexodus.desync.com%3A6969","seeders":34,"leechers":5,"uploader":null,"files":10,"time":1474048078,"description":"General\r\nCredit/Source                            : Original Ripper (Unknown)\r\nComplete name                            : Raaz.Reboot.2016.DesiScrRip.1CD.x264.AAC-Kp.mp4\r\nFormat                                   : MPEG-4\r\nFormat profile                           : Base Media / Version 2\r\nCodec ID                                 : mp42 (isom/iso2/avc1/mp41)\r\nFile size                                : 666 MiB\r\nDuration                                 : 2 h 7 min\r\nOverall bit rate mode                    : Variable\r\nOverall bit rate                         : 730 kb/s\r\n\r\nVideo\r\nID                                       : 1\r\nFormat                                   : AVC\r\nFormat/Info                              : Advanced Video Codec\r\nFormat profile                           :   \r\nFormat settings, CABAC                   : Yes\r\nFormat settings, ReFrames                : 4 frames\r\nCodec ID                                 : avc1\r\nCodec ID/Info                            : Advanced Video Coding\r\nDuration                                 : 2 h 7 min\r\nBit rate                                 : 652 kb/s\r\nWidth                                    : 640 pixels\r\nHeight                                   : 272 pixels\r\nDisplay aspect ratio                     : 2.35:1\r\nFrame rate mode                          : Variable\r\nFrame rate                               : 24.975 (24975/1000) FPS\r\nMinimum frame rate                       : 24.972 FPS\r\nMaximum frame rate                       : 24.979 FPS\r\nColor space                              : YUV\r\nChroma subsampling                       : 4:2:0\r\nBit depth                                : 8 bits\r\nScan type                                : Progressive\r\nBits/(Pixel*Frame)                       : 0.150\r\nWriting library                          : x264 core 142 r2491 24e4fed\r\nColor range                              : Limited\r\nColor primaries                          : BT.601 NTSC\r\nTransfer characteristics                 : BT.709\r\nMatrix coefficients                      : BT.601\r\n\r\nAudio\r\nID                                       : 2\r\nFormat                                   : AAC\r\nFormat/Info                              : Advanced Audio Codec\r\nFormat profile                           : LC\r\nCodec ID                                 : 40\r\nDuration                                 : 2 h 7 min\r\nBit rate mode                            : Variable\r\nBit rate                                 : 64.4 kb/s\r\nChannel(s)                               : 2 channels\r\nChannel positions                        : Front: L R\r\nSampling rate                            : 32.0 kHz\r\nFrame rate                               : 31.250 FPS (1024 spf)\r\nCompression mode                         : Lossy","torrent":{"xt":"urn:btih:d726d7422000b5a43e1f3900a914064def99aa10","amp;dn":"Raaz+Reboot+%282016%29+Hindi+DesiScrRip+1CD+x264+AAC+%5BKp%5D","amp;tr":["udp%3A%2F%2Ftracker.leechers-paradise.org%3A6969","udp%3A%2F%2Fzer0day.ch%3A1337","udp%3A%2F%2Fopen.demonii.com%3A1337","udp%3A%2F%2Ftracker.coppersurfer.tk%3A6969","udp%3A%2F%2Fexodus.desync.com%3A6969"],"infoHash":"d726d7422000b5a43e1f3900a914064def99aa10","infoHashBuffer":{"type":"Buffer","data":[215,38,215,66,32,0,181,164,62,31,57,0,169,20,6,77,239,153,170,16]},"announce":[],"urlList":[]}}