{"title":"Unknown Mortal Orchestra- (2013) II  Projeto Chernobyl","uid":8364817,"size":78933120,"categoryP":"audio","categoryS":"music","magnet":"?xt=urn:btih:dd67afe6f7bbc556858b91bd991c981f4aa1686b&amp;dn=Unknown+Mortal+Orchestra-+%282013%29+II++Projeto+Chernobyl&amp;tr=udp%3A%2F%2Ftracker.openbittorrent.com%3A80&amp;tr=udp%3A%2F%2Fopen.demonii.com%3A1337&amp;tr=udp%3A%2F%2Ftracker.coppersurfer.tk%3A6969&amp;tr=udp%3A%2F%2Fexodus.desync.com%3A6969","seeders":21,"leechers":2,"uploader":"klinho","files":11,"time":1365737722,"description":"II is the sophomore record from the band Unknown Mortal Orchestra.\n\n01 From The Sun 4:43\n02 Swim And Sleep (Like A Shark) 2:45\n03 So Good At Being In Trouble 3:50\n04 One At A Time 2:28\n05 The Opposite Of Afternoon 5:25\n06 No Need For A Leader 5:44\n07 Monki 7:18\n08 Dawn 1:08\n09 Faded In The Morning 4:21\n10 Secret Xtians 2:43","torrent":{"xt":"urn:btih:dd67afe6f7bbc556858b91bd991c981f4aa1686b","amp;dn":"Unknown+Mortal+Orchestra-+%282013%29+II++Projeto+Chernobyl","amp;tr":["udp%3A%2F%2Ftracker.openbittorrent.com%3A80","udp%3A%2F%2Fopen.demonii.com%3A1337","udp%3A%2F%2Ftracker.coppersurfer.tk%3A6969","udp%3A%2F%2Fexodus.desync.com%3A6969"],"infoHash":"dd67afe6f7bbc556858b91bd991c981f4aa1686b","infoHashBuffer":{"type":"Buffer","data":[221,103,175,230,247,187,197,86,133,139,145,189,153,28,152,31,74,161,104,107]},"announce":[],"urlList":[]}}