{"title":"Angie.Tribeca.S02E05.HDTV.x264-LOL[ettv]","uid":15122828,"size":108884969,"categoryP":"video","categoryS":"tv_shows","magnet":"?xt=urn:btih:fb0695e59db5f9e927a905e8673b82b3be70cb01&amp;dn=Angie.Tribeca.S02E05.HDTV.x264-LOL%5Bettv%5D&amp;tr=udp%3A%2F%2Ftracker.leechers-paradise.org%3A6969&amp;tr=udp%3A%2F%2Fzer0day.ch%3A1337&amp;tr=udp%3A%2F%2Fopen.demonii.com%3A1337&amp;tr=udp%3A%2F%2Ftracker.coppersurfer.tk%3A6969&amp;tr=udp%3A%2F%2Fexodus.desync.com%3A6969","seeders":22,"leechers":1,"uploader":"ettv","files":2,"time":1467084632,"description":"\nettv - ExtraTorrent TV Shows\r\n\n\nAngie.Tribeca.S02E05.HDTV.x264-LOL \r\n\n\n[Format]:    Matroska\n[Duration]:    21mn 9s\n[Resolution]:  720 x 400 pixels\n[Display aspect ratio]:    16:9\n[Frame rate mode]:    Constant\n[Frame rate]:    23.976 fps\n\r\n\n#ettv -&gt; To avoid fakes, ALWAYS check that the torrent was added by ettv\r \nhttp://extratorrent.cc/\r\n\n\nHelp us by donating with Bitcoin: 1MbtePmWNM13SEkQgmxF6RSvfaXugF7rpz\r\n\nScreens...\r \nhttp://extraimago.com/image/aDdU","torrent":{"xt":"urn:btih:fb0695e59db5f9e927a905e8673b82b3be70cb01","amp;dn":"Angie.Tribeca.S02E05.HDTV.x264-LOL%5Bettv%5D","amp;tr":["udp%3A%2F%2Ftracker.leechers-paradise.org%3A6969","udp%3A%2F%2Fzer0day.ch%3A1337","udp%3A%2F%2Fopen.demonii.com%3A1337","udp%3A%2F%2Ftracker.coppersurfer.tk%3A6969","udp%3A%2F%2Fexodus.desync.com%3A6969"],"infoHash":"fb0695e59db5f9e927a905e8673b82b3be70cb01","infoHashBuffer":{"type":"Buffer","data":[251,6,149,229,157,181,249,233,39,169,5,232,103,59,130,179,190,112,203,1]},"announce":[],"urlList":[]}}